nitrado/__init__.py
nitrado/nitrado.py
nitrado/py.typed
nitrado/games/__init__.py
nitrado/games/ark/__init__.py
nitrado/games/ark/arkserver.py
nitrado/games/ark/query.py
nitrado/games/ark/game_specific/__init__.py
nitrado/games/ark/game_specific/game_features.py
nitrado/games/ark/game_specific/game_specific.py
nitrado/games/ark/settings/__init__.py
nitrado/games/ark/settings/config.py
nitrado/games/ark/settings/feature_settings.py
nitrado/games/ark/settings/game_ini.py
nitrado/games/ark/settings/general.py
nitrado/games/ark/settings/settings.py
nitrado/games/ark/settings/start_param.py
nitrado/gameserver/__init__.py
nitrado/gameserver/credentials.py
nitrado/gameserver/gameserver.py
nitrado/gameserver/host_systems.py
nitrado/gameserver/operating_system.py
nitrado/gameserver/players.py
nitrado/globals/__init__.py
nitrado/globals/game.py
nitrado/globals/globals.py
nitrado/globals/locations.py
nitrado/globals/maintenance.py
nitrado/globals/token.py
nitrado/lib/__init__.py
nitrado/lib/client.py
nitrado/lib/errors.py
nitrado/oauth/__init__.py
nitrado/service/__init__.py
nitrado/service/action.py
nitrado/service/arguments.py
nitrado/service/details.py
nitrado/service/log.py
nitrado/service/logs_page.py
nitrado/service/notification.py
nitrado/service/service.py
nitrado/service/task.py
nitrado-1.0.33.dist-info/LICENSE
nitrado-1.0.33.dist-info/METADATA
nitrado-1.0.33.dist-info/WHEEL
nitrado-1.0.33.dist-info/top_level.txt
nitrado-1.0.33.dist-info/RECORD
